setup.py
TGWebServices.egg-info/PKG-INFO
TGWebServices.egg-info/SOURCES.txt
TGWebServices.egg-info/dependency_links.txt
TGWebServices.egg-info/entry_points.txt
TGWebServices.egg-info/not-zip-safe
TGWebServices.egg-info/requires.txt
TGWebServices.egg-info/top_level.txt
tgwebservices/__init__.py
tgwebservices/controllers.py
tgwebservices/iconv.py
tgwebservices/release.py
tgwebservices/runtime.py
tgwebservices/soap.py
tgwebservices/xml_.py
tgwebservices/templates/__init__.py
tgwebservices/tests/__init__.py
tgwebservices/tests/fixtures.py
tgwebservices/tests/test_controllers.py
tgwebservices/tests/test_json.py
tgwebservices/tests/test_soap.py
tgwebservices/tests/test_xml.py