Metadata-Version: 1.0
Name: TGWebServices
Version: 1.2.4
Summary: Multiprotocol Web Services for TurboGears 1.x
Home-page: http://code.google.com/p/tgws/
Author: Kevin Dangoor, Christophe de Vienne
Author-email: turbogears-web-services@googlegroups.com
License: MIT
Keywords: turbogears.extension
Platform: UNKNOWN
Classifier: Development Status :: 3 - Production/Stable
Classifier: Operating System :: OS Independent
Classifier: Programming Language :: Python
Classifier: Topic :: Software Development :: Libraries :: Python Modules
Classifier: Framework :: TurboGears
